tagcounter/__init__.py
tagcounter/__main__.py
tagcounter/console.py
tagcounter/data.pickle
tagcounter/domains.yaml
tagcounter/gui.py
tagcounter/htmlParser.py
tagcounter/htmlReader.py
tagcounter/parser.db
tagcounter/tagService.py
tagcounter/urlParser.py
tagcounter/yamlService.py
tagcounter/DB/__init__.py
tagcounter/DB/domainRepo.py
tagcounter/DB/pageRepo.py
tagcounter/DB/models/__init__.py
tagcounter/DB/models/domain.py
tagcounter/DB/models/page.py
htmltc-1.0.1.dist-info/METADATA
htmltc-1.0.1.dist-info/WHEEL
htmltc-1.0.1.dist-info/entry_points.txt
htmltc-1.0.1.dist-info/top_level.txt
htmltc-1.0.1.dist-info/RECORD
