Metadata-Version: 2.1
Name: htmltc
Version: 1.0.1
Summary: app for counting tag of site page
Home-page: https://github.com/alenavysotskaya4324/tagcounter
Author: Elena Vysotskaya
Author-email: UNKNOWN
License: UNKNOWN
Platform: UNKNOWN
